lazychoices/__init__.py
lazychoices/compat.py
lazychoices/utils.py
lazychoices/admin/__init__.py
lazychoices/admin/checks.py
lazychoices/admin/filters.py
lazychoices/admin/mixins.py
lazychoices/forms/__init__.py
lazychoices/forms/fields.py
lazychoices/forms/models.py
lazychoices/models/__init__.py
lazychoices/models/fields.py
lazychoices/models/mixins.py
django_lazy_choices-0.2.0.dist-info/top_level.txt
django_lazy_choices-0.2.0.dist-info/METADATA
django_lazy_choices-0.2.0.dist-info/DESCRIPTION.rst
django_lazy_choices-0.2.0.dist-info/metadata.json
django_lazy_choices-0.2.0.dist-info/WHEEL
django_lazy_choices-0.2.0.dist-info/RECORD
