Metadata-Version: 2.0
Name: django-lazy-choices
Version: 0.2.0
Summary: Lazy choices for Django models
Home-page: https://github.com/jamieconnolly/django-lazy-choices
Author: Jamie Connolly
Author-email: jamie@jamieconnolly.com
License: MIT
Keywords: django
Platform: UNKNOWN
Classifier: Development Status :: 3 - Alpha
Classifier: Environment :: Web Environment
Classifier: Framework :: Django :: 1.8
Classifier: Framework :: Django :: 1.9
Classifier: Intended Audience :: Developers
Classifier: License :: OSI Approved :: MIT License
Classifier: Natural Language :: English
Classifier: Operating System :: OS Independent
Classifier: Programming Language :: Python :: 2
Classifier: Programming Language :: Python :: 2.7
Classifier: Programming Language :: Python :: 3
Classifier: Programming Language :: Python :: 3.3
Classifier: Programming Language :: Python :: 3.4
Classifier: Programming Language :: Python :: 3.5
Classifier: Topic :: Internet :: WWW/HTTP
Classifier: Topic :: Software Development :: Libraries :: Python Modules
Requires-Dist: Django (>=1.8,<1.10)
Provides-Extra: dev
Requires-Dist: flake8 (>=2.5,<2.6); extra == 'dev'
Requires-Dist: isort (>=4.2,<4.3); extra == 'dev'
